dhl_express_lib/__init__.py
dhl_express_lib/book_pickup_global_req_3_0.py
dhl_express_lib/book_pickup_global_res_3_0.py
dhl_express_lib/cancel_pickup_global_req_3_0.py
dhl_express_lib/cancel_pickup_global_res.py
dhl_express_lib/datatypes.py
dhl_express_lib/datatypes_global.py
dhl_express_lib/datatypes_global_v10.py
dhl_express_lib/datatypes_global_v62.py
dhl_express_lib/datatypes_global_v62b.py
dhl_express_lib/dct_req_global_3_0.py
dhl_express_lib/dct_requestdatatypes.py
dhl_express_lib/dct_requestdatatypes_global.py
dhl_express_lib/dct_response_global_3_0.py
dhl_express_lib/dct_responsedatatypes_global.py
dhl_express_lib/err_res.py
dhl_express_lib/modify_pickup_global_req_3_0.py
dhl_express_lib/modify_pickup_global_res_3_0.py
dhl_express_lib/pickup_err_res.py
dhl_express_lib/pickup_res.py
dhl_express_lib/pickupdatatypes_global.py
dhl_express_lib/pickupdatatypes_global_3_0.py
dhl_express_lib/routing_global_req_2_0.py
dhl_express_lib/routing_global_res.py
dhl_express_lib/ship_val_err_res.py
dhl_express_lib/ship_val_global_req_10_0.py
dhl_express_lib/ship_val_global_res_10_0.py
dhl_express_lib/track_err_res.py
dhl_express_lib/tracking_request_known_1_0.py
dhl_express_lib/tracking_request_unknown_1_0.py
dhl_express_lib/tracking_response.py
carrier.dhl_express-2023.4.dist-info/METADATA
carrier.dhl_express-2023.4.dist-info/WHEEL
carrier.dhl_express-2023.4.dist-info/top_level.txt
carrier.dhl_express-2023.4.dist-info/RECORD
